boardgames/__init__.py
boardgames/_board.py
boardgames/_cell.py
boardgames/py.typed
boardgames-1.0.1.dist-info/LICENSE
boardgames-1.0.1.dist-info/WHEEL
boardgames-1.0.1.dist-info/METADATA
boardgames-1.0.1.dist-info/RECORD
